[
  {
    "release_date": "2013-09-18",
    "title": "Thirst, ceci est mon sang",
    "director": "Park Chan-wook",
    "image_path": "images/2013-09-18_thirst_ceci_est_mon_sang.jpg"
  },
  {
    "release_date": "2013-09-18",
    "title": "Riddick",
    "director": "David Twohy",
    "image_path": "images/2013-09-18_riddick.jpg"
  },
  {
    "release_date": "2013-09-18",
    "title": "Les Invincibles",
    "director": "Frédéric Berthe",
    "image_path": "images/2013-09-18_les_invincibles.jpg"
  },
  {
    "release_date": "2013-09-18",
    "title": "Elle s'en va",
    "director": "Emmanuelle Bercot , George Merritt",
    "image_path": "images/2013-09-18_elle_sen_va.jpg"
  },
  {
    "release_date": "2013-09-18",
    "title": "Les Miller, une famille en herbe",
    "director": "Rawson Marshall Thurber",
    "image_path": "images/2013-09-18_les_miller_une_famille_en_herbe.jpg"
  },
  {
    "release_date": "2013-09-18",
    "title": "Ma Vie avec Liberace",
    "director": "Steven Soderbergh",
    "image_path": "images/2013-09-18_ma_vie_avec_liberace.jpg"
  },
  {
    "release_date": "2013-09-18",
    "title": "Moi et toi",
    "director": "Bernardo Bertolucci",
    "image_path": "images/2013-09-18_moi_et_toi.jpg"
  },
  {
    "release_date": "2013-09-18",
    "title": "Vietnam Paradiso",
    "director": "Julien Lahmi",
    "image_path": "images/2013-09-18_vietnam_paradiso.jpg"
  },
  {
    "release_date": "2013-09-18",
    "title": "Oggy et les cafards, le film",
    "director": "Olivier Jean-Marie , Olivier Marie",
    "image_path": "images/2013-09-18_oggy_et_les_cafards_le_film.jpg"
  },
  {
    "release_date": "2013-09-18",
    "title": "Les Amants du Texas",
    "director": "David lowery",
    "image_path": "images/2013-09-18_les_amants_du_texas.jpg"
  },
  {
    "release_date": "2013-09-18",
    "title": "The Conspiracy",
    "director": "Christopher MacBride",
    "image_path": "images/2013-09-18_the_conspiracy.jpg"
  },
  {
    "release_date": "2013-09-18",
    "title": "Barcelona avant que le temps ne l'efface",
    "director": "Mireia Ros",
    "image_path": "images/2013-09-18_barcelona_avant_que_le_temps_ne_lefface.jpg"
  },
  {
    "release_date": "2013-09-18",
    "title": "Il était une fois en Yougoslavie : Cinema Komunisto",
    "director": "Mila Turajlic , Mila Turajilic",
    "image_path": "images/2013-09-18_il_etait_une_fois_en_yougoslavie_cinema_komunisto.jpg"
  },
  {
    "release_date": "2013-09-18",
    "title": "Le Monde Doit M'arriver (?)",
    "director": "Jonathan Taïeb",
    "image_path": "images/2013-09-18_le_monde_doit_marriver_.jpg"
  },
  {
    "release_date": "2013-09-18",
    "title": "Obsession",
    "director": "Brian de Palma",
    "image_path": "images/2013-09-18_obsession.jpg"
  }
]