[
  {
    "release_date": "2006-01-11",
    "title": "Jarhead, la fin de l'innocence",
    "director": "Sam Mendes",
    "image_path": "images/2006-01-11_jarhead_la_fin_de_linnocence.jpg"
  },
  {
    "release_date": "2006-01-11",
    "title": "Le Boss",
    "director": "Les Mayfield",
    "image_path": "images/2006-01-11_le_boss.jpg"
  },
  {
    "release_date": "2006-01-11",
    "title": "La Rumeur court...",
    "director": "Rob Reiner",
    "image_path": "images/2006-01-11_la_rumeur_court.jpg"
  },
  {
    "release_date": "2006-01-11",
    "title": "Reinas",
    "director": "Manuel Gomez Pereira",
    "image_path": "images/2006-01-11_reinas.jpg"
  },
  {
    "release_date": "2006-01-11",
    "title": "Les Copains",
    "director": "Michel Bouquet , Yves Robert",
    "image_path": "images/2006-01-11_les_copains.jpg"
  },
  {
    "release_date": "2006-01-11",
    "title": "La Crypte",
    "director": "Bruce Hunt",
    "image_path": "images/2006-01-11_la_crypte.jpg"
  },
  {
    "release_date": "2006-01-11",
    "title": "Animal",
    "director": "Rose Bosch",
    "image_path": "images/2006-01-11_animal.jpg"
  },
  {
    "release_date": "2006-01-11",
    "title": "George Michael : mon histoire",
    "director": "Southan Morris",
    "image_path": "images/2006-01-11_george_michael_mon_histoire.jpg"
  },
  {
    "release_date": "2006-01-11",
    "title": "La Mort de Dante Lazarescu",
    "director": "Cristi Puiu",
    "image_path": "images/2006-01-11_la_mort_de_dante_lazarescu.jpg"
  },
  {
    "release_date": "2006-01-11",
    "title": "Le Plafond de verre",
    "director": "Yamina Benguigui",
    "image_path": "images/2006-01-11_le_plafond_de_verre.jpg"
  },
  {
    "release_date": "2006-01-11",
    "title": "Docteur Patch",
    "director": "Tom Shadyac",
    "image_path": "images/2006-01-11_docteur_patch.jpg"
  },
  {
    "release_date": "2006-01-11",
    "title": "La charge des tuniques bleues",
    "director": "Anthony Mann",
    "image_path": "images/2006-01-11_la_charge_des_tuniques_bleues.jpg"
  },
  {
    "release_date": "2006-01-11",
    "title": "La Légende du grand judo",
    "director": "Akira Kurosawa"
  },
  {
    "release_date": "2006-01-11",
    "title": "La Nouvelle Légende du grand judo",
    "director": "Akira Kurosawa"
  },
  {
    "release_date": "2006-01-11",
    "title": "Le Bal des chattes sauvages",
    "director": "Veronika Minder",
    "image_path": "images/2006-01-11_le_bal_des_chattes_sauvages.jpg"
  },
  {
    "release_date": "2006-01-11",
    "title": "Les Corps ouverts",
    "director": "Sébastien Lifshitz , Sybil Danning"
  },
  {
    "release_date": "2006-01-11",
    "title": "Odete",
    "director": "Joao Pedro Rodrigues",
    "image_path": "images/2006-01-11_odete.jpg"
  },
  {
    "release_date": "2006-01-11",
    "title": "Oliva Oliva",
    "director": "Peter Hoffman"
  },
  {
    "release_date": "2006-01-11",
    "title": "Silent Running",
    "director": "Douglas Trumbull",
    "image_path": "images/2006-01-11_silent_running.jpg"
  }
]