[
  {
    "release_date": "2008-07-16",
    "title": "Voyage au centre de la Terre",
    "director": "Eric Brevig",
    "image_path": "images/2008-07-16_voyage_au_centre_de_la_terre.jpg"
  },
  {
    "release_date": "2008-07-16",
    "title": "Voyage au centre de la Terre, 3D",
    "director": "Eric Brevig",
    "image_path": "images/2008-07-16_voyage_au_centre_de_la_terre_3d.jpg"
  },
  {
    "release_date": "2008-07-16",
    "title": "Les Proies",
    "director": "Gonzalo Lopez-Gallego",
    "image_path": "images/2008-07-16_les_proies.jpg"
  },
  {
    "release_date": "2008-07-16",
    "title": "L'Île nue",
    "director": "Kaneto Shindo"
  },
  {
    "release_date": "2008-07-16",
    "title": "Nos 18 ans",
    "director": "Frédéric Berthe",
    "image_path": "images/2008-07-16_nos_18_ans.jpg"
  },
  {
    "release_date": "2008-07-16",
    "title": "Spartatouille",
    "director": "Aaron Seltzer , Jason Friedberg",
    "image_path": "images/2008-07-16_spartatouille.jpg"
  },
  {
    "release_date": "2008-07-16",
    "title": "Broken English",
    "director": "Zoe R. Cassavetes , Zoe Cassavetes , Zoe R Cassavetes",
    "image_path": "images/2008-07-16_broken_english.jpg"
  },
  {
    "release_date": "2008-07-16",
    "title": "Fool Moon",
    "director": "Jérôme L'Hotsky",
    "image_path": "images/2008-07-16_fool_moon.jpg"
  },
  {
    "release_date": "2008-07-16",
    "title": "Glory to the Filmmaker!",
    "director": "Takeshi Kitano",
    "image_path": "images/2008-07-16_glory_to_the_filmmaker.jpg"
  },
  {
    "release_date": "2008-07-16",
    "title": "Vera Drake",
    "director": "Mike Leigh",
    "image_path": "images/2008-07-16_vera_drake.jpg"
  },
  {
    "release_date": "2008-07-16",
    "title": "Biutiful Cauntri",
    "director": "Esmeralda Calabria , Andrea d'Ambrosio , Peppe Ruggiero"
  },
  {
    "release_date": "2008-07-16",
    "title": "Un monde à nous",
    "director": "Frédéric Balekdjian",
    "image_path": "images/2008-07-16_un_monde_a_nous.jpg"
  },
  {
    "release_date": "2008-07-16",
    "title": "Soit je meurs, soit je vais mieux",
    "director": "Laurence Ferreira Barbosa",
    "image_path": "images/2008-07-16_soit_je_meurs_soit_je_vais_mieux.jpg"
  },
  {
    "release_date": "2008-07-16",
    "title": "Blacula, le vampire noir",
    "director": "William Crain",
    "image_path": "images/2008-07-16_blacula_le_vampire_noir.jpg"
  },
  {
    "release_date": "2008-07-16",
    "title": "Harold et Kumar s'évadent de Guantanamo",
    "director": "Hayden Schlossberg , Jon Hurwitz",
    "image_path": "images/2008-07-16_harold_et_kumar_sevadent_de_guantanamo.jpg"
  },
  {
    "release_date": "2008-07-16",
    "title": "Lake Tahoe",
    "director": "Fernando Eimbcke"
  },
  {
    "release_date": "2008-07-16",
    "title": "VHS Kahloucha",
    "director": "Nejid Belkadhi , Nejib Belkadhi"
  }
]