[
  {
    "release_date": "2018-04-11",
    "title": "Série Noire",
    "director": "Alain Corneau",
    "image_path": "images/2018-04-11_serie_noire.jpg"
  },
  {
    "release_date": "2018-04-11",
    "title": "Mad Max : Fury Road",
    "director": "George Miller , Georgea Miller",
    "image_path": "images/2018-04-11_mad_max_fury_road.jpg"
  },
  {
    "release_date": "2018-04-11",
    "title": "Luna",
    "director": "Elsa Diringer",
    "image_path": "images/2018-04-11_luna.jpg"
  },
  {
    "release_date": "2018-04-11",
    "title": "Rampage",
    "director": "Brad Peyton",
    "image_path": "images/2018-04-11_rampage.jpg"
  },
  {
    "release_date": "2018-04-11",
    "title": "Sherlock Gnomes",
    "director": "John Stevenson , Steve Pink",
    "image_path": "images/2018-04-11_sherlock_gnomes.jpg"
  },
  {
    "release_date": "2018-04-11",
    "title": "Kings",
    "director": "Deniz Gamze Ergüven",
    "image_path": "images/2018-04-11_kings.jpg"
  },
  {
    "release_date": "2018-04-11",
    "title": "The Third Murder",
    "director": "Hirokazu Kore-eda",
    "image_path": "images/2018-04-11_the_third_murder.jpg"
  },
  {
    "release_date": "2018-04-11",
    "title": "On a 20 ans pour changer le monde",
    "director": "Hélène Médigue",
    "image_path": "images/2018-04-11_on_a_20_ans_pour_changer_le_monde.jpg"
  },
  {
    "release_date": "2018-04-11",
    "title": "Le Redoutable",
    "director": "Michel Hazanavicius , Tino Rossi",
    "image_path": "images/2018-04-11_le_redoutable.jpg"
  },
  {
    "release_date": "2018-04-11",
    "title": "4 ans en 10 minutes",
    "director": "Mladen Kovacevic"
  },
  {
    "release_date": "2018-04-11",
    "title": "70 ans de silence : Espagne, mémoires et transmission",
    "director": "Emile Navarro"
  },
  {
    "release_date": "2018-04-11",
    "title": "Anubis",
    "director": "Chris Wedge"
  },
  {
    "release_date": "2018-04-11",
    "title": "A Quiet Place",
    "director": "John Krasinski"
  },
  {
    "release_date": "2018-04-11",
    "title": "Benvenuto Cellini (De Nationale Opera-FRA Cinéma)",
    "director": "Terry Gilliam"
  },
  {
    "release_date": "2018-04-11",
    "title": "Du soleil dans mes yeux",
    "director": "Nicolas Giraud",
    "image_path": "images/2018-04-11_du_soleil_dans_mes_yeux.jpg"
  },
  {
    "release_date": "2018-04-11",
    "title": "L'héroïque lande",
    "director": "Nicolas Klotz , Elisabeth Perceval",
    "image_path": "images/2018-04-11_lheroique_lande.jpg"
  },
  {
    "release_date": "2018-04-11",
    "title": "Luisa Miller"
  },
  {
    "release_date": "2018-04-11",
    "title": "Mercury",
    "director": "Karthik Subbaraj",
    "image_path": "images/2018-04-11_mercury.jpg"
  },
  {
    "release_date": "2018-04-11",
    "title": "Plutôt mourir que mourir",
    "director": "Natacha Nisic",
    "image_path": "images/2018-04-11_plutot_mourir_que_mourir.jpg"
  },
  {
    "release_date": "2018-04-11",
    "title": "Southern Belle",
    "director": "Nicolas Peduzzi",
    "image_path": "images/2018-04-11_southern_belle.jpg"
  },
  {
    "release_date": "2018-04-11",
    "title": "Winter Brothers",
    "director": "Hlynur Palmason",
    "image_path": "images/2018-04-11_winter_brothers.jpg"
  }
]