[
  {
    "release_date": "2025-03-12",
    "title": "On ira",
    "director": "Enya Baroux",
    "image_path": "images/2025-03-12_on_ira.jpg"
  },
  {
    "release_date": "2025-03-12",
    "title": "Black Box Diaries",
    "director": "Shiori Ito",
    "image_path": "images/2025-03-12_black_box_diaries.jpg"
  },
  {
    "release_date": "2025-03-12",
    "title": "L'Oreille",
    "director": "Karel Kachyna",
    "image_path": "images/2025-03-12_loreille.jpg"
  },
  {
    "release_date": "2025-03-12",
    "title": "Vers un pays inconnu",
    "director": "Fleifel",
    "image_path": "images/2025-03-12_vers_un_pays_inconnu.jpg"
  },
  {
    "release_date": "2025-03-12",
    "title": "Avishai Cohen à l'Olympia",
    "director": "Amos Rozenberg",
    "image_path": "images/2025-03-12_avishai_cohen_a_lolympia.jpg"
  },
  {
    "release_date": "2025-03-12",
    "title": "Berlin, été 42",
    "director": "Andreas Dresen",
    "image_path": "images/2025-03-12_berlin_ete_42.jpg"
  },
  {
    "release_date": "2025-03-12",
    "title": "Blue Sun Palace",
    "director": "Constance Tsang",
    "image_path": "images/2025-03-12_blue_sun_palace.jpg"
  },
  {
    "release_date": "2025-03-12",
    "title": "Délocalisés",
    "director": "Redouane Bougheraba , Ali Bougheraba",
    "image_path": "images/2025-03-12_delocalises.jpg"
  },
  {
    "release_date": "2025-03-12",
    "title": "Dounia, le grand pays blanc",
    "director": "André Kadi , Marya Zarif",
    "image_path": "images/2025-03-12_dounia_le_grand_pays_blanc.jpg"
  },
  {
    "release_date": "2025-03-12",
    "title": "Groupe Mario, la résistance oubliée",
    "director": "Dominique Hennequin"
  },
  {
    "release_date": "2025-03-12",
    "title": "Jeunesse imaginaire",
    "image_path": "images/2025-03-12_jeunesse_imaginaire.jpg"
  },
  {
    "release_date": "2025-03-12",
    "title": "La Convocation",
    "director": "Halfdan Tøndel",
    "image_path": "images/2025-03-12_la_convocation.jpg"
  },
  {
    "release_date": "2025-03-12",
    "title": "L'Âge imminent",
    "director": "Gerard Gimeno , Clara Llorens",
    "image_path": "images/2025-03-12_lage_imminent.jpg"
  },
  {
    "release_date": "2025-03-12",
    "title": "L'aube de l'impressionnisme : Paris 1874",
    "director": "Ali Ray",
    "image_path": "images/2025-03-12_laube_de_limpressionnisme_paris_1874.jpg"
  },
  {
    "release_date": "2025-03-12",
    "title": "Legends of the Condor Heroes : The Gallants",
    "director": "Tsui Hark"
  },
  {
    "release_date": "2025-03-12",
    "title": "Les loups",
    "director": "Isabelle Prim"
  },
  {
    "release_date": "2025-03-12",
    "title": "Les loups",
    "director": "Isabelle Prim"
  },
  {
    "release_date": "2025-03-12",
    "title": "Le soleil se lèvera",
    "director": "Ayat Najafi",
    "image_path": "images/2025-03-12_le_soleil_se_levera.jpg"
  },
  {
    "release_date": "2025-03-12",
    "title": "Love in a Fallen City",
    "director": "Ann Hui",
    "image_path": "images/2025-03-12_love_in_a_fallen_city.jpg"
  },
  {
    "release_date": "2025-03-12",
    "title": "Mayonnaise",
    "director": "Giulia Grandinetti"
  },
  {
    "release_date": "2025-03-12",
    "title": "Mobile Suit Gundam GQuuuuuuX-Beginning",
    "director": "Kazuya Tsurumaki",
    "image_path": "images/2025-03-12_mobile_suit_gundam_gquuuuuux-beginning.jpg"
  },
  {
    "release_date": "2025-03-12",
    "title": "Parthenope",
    "director": "Paolo Sorrentino",
    "image_path": "images/2025-03-12_parthenope.jpg"
  },
  {
    "release_date": "2025-03-12",
    "title": "Passeport pour l'enfer",
    "director": "Ann Hui , Isa Miranda",
    "image_path": "images/2025-03-12_passeport_pour_lenfer.jpg"
  },
  {
    "release_date": "2025-03-12",
    "title": "Reine mère",
    "director": "Manèle Labidi",
    "image_path": "images/2025-03-12_reine_mere.jpg"
  },
  {
    "release_date": "2025-03-12",
    "title": "The Insider",
    "director": "Steven Soderbergh",
    "image_path": "images/2025-03-12_the_insider.jpg"
  },
  {
    "release_date": "2025-03-12",
    "title": "The Last Showgirl",
    "director": "Gia Coppola",
    "image_path": "images/2025-03-12_the_last_showgirl.jpg"
  },
  {
    "release_date": "2025-03-12",
    "title": "The Metropolitan Opera: Fidelio",
    "director": "Jürgen Flimm",
    "image_path": "images/2025-03-12_the_metropolitan_opera_fidelio.jpg"
  },
  {
    "release_date": "2025-03-12",
    "title": "Women (version restaurée)",
    "director": "Stanley Kwan",
    "image_path": "images/2025-03-12_women_version_restauree.jpg"
  }
]