[
  {
    "release_date": "2009-06-10",
    "title": "Dancing Girls",
    "director": "Darren Grant",
    "image_path": "images/2009-06-10_dancing_girls.jpg"
  },
  {
    "release_date": "2009-06-10",
    "title": "Je vais te manquer",
    "director": "Amanda Sthers",
    "image_path": "images/2009-06-10_je_vais_te_manquer.jpg"
  },
  {
    "release_date": "2009-06-10",
    "title": "Les Beaux Gosses",
    "director": "Riad Sattouf , Ria Sattouf",
    "image_path": "images/2009-06-10_les_beaux_gosses.jpg"
  },
  {
    "release_date": "2009-06-10",
    "title": "La Nonne",
    "director": "Luis De La Madrid",
    "image_path": "images/2009-06-10_la_nonne.jpg"
  },
  {
    "release_date": "2009-06-10",
    "title": "Jaffa",
    "director": "Keren Yedaya"
  },
  {
    "release_date": "2009-06-10",
    "title": "Sunshine Cleaning",
    "director": "Christine Jeffs",
    "image_path": "images/2009-06-10_sunshine_cleaning.jpg"
  },
  {
    "release_date": "2009-06-10",
    "title": "Story of Jen",
    "director": "François Rotger",
    "image_path": "images/2009-06-10_story_of_jen.jpg"
  },
  {
    "release_date": "2009-06-10",
    "title": "Viridiana",
    "director": "Luis Bunuel",
    "image_path": "images/2009-06-10_viridiana.jpg"
  },
  {
    "release_date": "2009-06-10",
    "title": "Coraline, en 3D",
    "director": "Henry Selick"
  },
  {
    "release_date": "2009-06-10",
    "title": "Dauphins et baleines, nomades des mers, 3D",
    "director": "Jean-Jacques Mantello"
  },
  {
    "release_date": "2009-06-10",
    "title": "L'Ange exterminateur",
    "director": "Luis Bunuel",
    "image_path": "images/2009-06-10_lange_exterminateur.jpg"
  },
  {
    "release_date": "2009-06-10",
    "title": "L'Herbe du rat",
    "director": "Julio Bressane"
  },
  {
    "release_date": "2009-06-10",
    "title": "Memories",
    "director": "Roland Richter"
  },
  {
    "release_date": "2009-06-10",
    "title": "Simon du désert, version restaurée",
    "director": "Luis Bunuel"
  },
  {
    "release_date": "2009-06-10",
    "title": "Toto qui vécut deux fois",
    "director": "Daniele Cipri , Francesco Maresto , Marcello Miranda , Edmond Richard",
    "image_path": "images/2009-06-10_toto_qui_vecut_deux_fois.jpg"
  }
]